dqlmagic/__init__.py
dqlmagic/dqlmagic.py
dqlmagic-1.3.0.dist-info/METADATA
dqlmagic-1.3.0.dist-info/WHEEL
dqlmagic-1.3.0.dist-info/top_level.txt
dqlmagic-1.3.0.dist-info/zip-safe
dqlmagic-1.3.0.dist-info/RECORD
