Metadata-Version: 2.1
Name: dqlmagic
Version: 1.3.0
Summary: IPython magic function for Dynatrace Query Language (DQL)
Home-page: https://github.com/dtPaTh/Dqlmagic
Author: Patrick Thurner
Author-email: patrick.thurner@dynatrace.com
License: Apache 2.0
Keywords: Notebook,Jupyter,DQL,Dynatrace Query Language
Classifier: License :: OSI Approved :: Apache Software License
Classifier: Programming Language :: Python :: 3
Requires-Dist: ipython
Requires-Dist: jupyter
Requires-Dist: python-dotenv
